<?xml version="1.0" encoding="UTF-8"?>
<qes:espresso xsi:schemaLocation="http://www.quantum-espresso.org/ns/qes/qes-1.0 http://www.quantum-espresso.org/ns/qes/qes_190304.xsd" Units="Hartree atomic units" xmlns:xsi="http://www.w3.org/2001/XMLSchema-instance" xmlns:qes="http://www.quantum-espresso.org/ns/qes/qes-1.0">
  <!--If not explicitely indicated, all quantities are expressed in Hartree atomic units-->
  <general_info>
    <xml_format NAME="QEXSD" VERSION="19.03">QEXSD_19.03</xml_format>
    <creator NAME="PWSCF" VERSION="6.4">XML file generated by PWSCF</creator>
    <created DATE="26Oct2021" TIME="18:16:23">This run was terminated on:  18:16:23  26 Oct 2021</created>
    <job></job>
  </general_info>
  <parallel_info>
    <nprocs>1</nprocs>
    <nthreads>1</nthreads>
    <ntasks>1</ntasks>
    <nbgrp>1</nbgrp>
    <npool>1</npool>
    <ndiag>1</ndiag>
  </parallel_info>
  <input>
    <control_variables>
      <title></title>
      <calculation>bands</calculation>
      <restart_mode>from_scratch</restart_mode>
      <prefix>Si_cubic</prefix>
      <pseudo_dir>../../pseudo</pseudo_dir>
      <outdir>./</outdir>
      <stress>false</stress>
      <forces>false</forces>
      <wf_collect>true</wf_collect>
      <disk_io>low</disk_io>
      <max_seconds>10000000</max_seconds>
      <nstep>1</nstep>
      <etot_conv_thr>5.000000000000000e-5</etot_conv_thr>
      <forc_conv_thr>5.000000000000000e-4</forc_conv_thr>
      <press_conv_thr>5.000000000000000e-1</press_conv_thr>
      <verbosity>high</verbosity>
      <print_every>100000</print_every>
    </control_variables>
    <atomic_species ntyp="2">
      <species name="Si">
        <pseudo_file>Si.pbe-rrkj.UPF</pseudo_file>
      </species>
      <species name="Ge">
        <mass>7.264000000000000e1</mass>
        <pseudo_file>Ge.pbe-kjpaw.UPF</pseudo_file>
      </species>
    </atomic_species>
    <atomic_structure nat="8" alat="1.034568287142e1">
      <atomic_positions>
        <atom name="Si" index="1">1.404406667437952e-3 1.404406667437952e-3 -4.473343261149537e-2</atom>
        <atom name="Si" index="2">2.587760345251342e0 2.587760345251342e0 2.517347977909821e0</atom>
        <atom name="Ge" index="3">5.174096277304679e0 1.115990995858547e-3 5.217030514893136e0</atom>
        <atom name="Ge" index="4">1.115990995858547e-3 5.174096277304679e0 5.217030514893136e0</atom>
        <atom name="Si" index="5">5.174106810638142e0 5.174106810638142e0 -4.501924801991594e-2</atom>
        <atom name="Ge" index="6">7.760456065260715e0 2.587475826195049e0 8.047598618895766e0</atom>
        <atom name="Ge" index="7">2.587475826195049e0 7.760456065260715e0 8.047598618895766e0</atom>
        <atom name="Si" index="8">7.760462539462447e0 7.760462539462447e0 2.517063043113779e0</atom>
      </atomic_positions>
      <cell>
        <a1>1.034568286400000e1 -2.734100000000000e-4 -2.808260000000000e-4</a1>
        <a2>-2.734100000000000e-4 1.034568286400000e1 -2.808260000000000e-4</a2>
        <a3>-2.734100000000000e-4 -2.734100000000000e-4 1.079211782200000e1</a3>
      </cell>
    </atomic_structure>
    <dft>
      <functional>pbe</functional>
    </dft>
    <spin>
      <lsda>false</lsda>
      <noncolin>false</noncolin>
      <spinorbit>false</spinorbit>
    </spin>
    <bands>
      <smearing degauss="5.000000000000e-4">gaussian</smearing>
      <tot_charge>0.000000000000000e0</tot_charge>
      <occupations>smearing</occupations>
    </bands>
    <basis>
      <gamma_only>false</gamma_only>
      <ecutwfc>1.500000000000000e1</ecutwfc>
      <ecutrho>6.000000000000000e1</ecutrho>
    </basis>
    <electron_control>
      <diagonalization>davidson</diagonalization>
      <mixing_mode>plain</mixing_mode>
      <mixing_beta>7.000000000000000e-1</mixing_beta>
      <conv_thr>5.000000000000000e-9</conv_thr>
      <mixing_ndim>8</mixing_ndim>
      <max_nstep>100</max_nstep>
      <real_space_q>false</real_space_q>
      <real_space_beta>false</real_space_beta>
      <tq_smoothing>false</tq_smoothing>
      <tbeta_smoothing>false</tbeta_smoothing>
      <diago_thr_init>0.000000000000000e0</diago_thr_init>
      <diago_full_acc>false</diago_full_acc>
      <diago_cg_maxiter>20</diago_cg_maxiter>
      <diago_ppcg_maxiter>20</diago_ppcg_maxiter>
    </electron_control>
    <k_points_IBZ>
      <nk>11</nk>
      <k_point weight="1.000000000000e0">0.000000000000000e0 0.000000000000000e0 0.000000000000000e0</k_point>
      <k_point weight="1.000000000000e0">1.301104319514717e-6 1.301104319514717e-6 4.793166205318520e-2</k_point>
      <k_point weight="1.000000000000e0">2.602208639029433e-6 2.602208639029433e-6 9.586332410637040e-2</k_point>
      <k_point weight="1.000000000000e0">3.903312958544150e-6 3.903312958544150e-6 1.437949861595556e-1</k_point>
      <k_point weight="1.000000000000e0">5.204417278058867e-6 5.204417278058867e-6 1.917266482127408e-1</k_point>
      <k_point weight="1.000000000000e0">6.505521597573583e-6 6.505521597573583e-6 2.396583102659259e-1</k_point>
      <k_point weight="1.000000000000e0">7.806625917088300e-6 7.806625917088300e-6 2.875899723191112e-1</k_point>
      <k_point weight="1.000000000000e0">9.107730236603016e-6 9.107730236603016e-6 3.355216343722964e-1</k_point>
      <k_point weight="1.000000000000e0">1.040883455611773e-5 1.040883455611773e-5 3.834532964254816e-1</k_point>
      <k_point weight="1.000000000000e0">1.170993887563245e-5 1.170993887563245e-5 4.313849584786667e-1</k_point>
      <k_point weight="1.000000000000e0">1.301104319514717e-5 1.301104319514717e-5 4.793166205318519e-1</k_point>
    </k_points_IBZ>
    <ion_control>
      <ion_dynamics>none</ion_dynamics>
      <upscale>1.000000000000000e2</upscale>
      <remove_rigid_rot>false</remove_rigid_rot>
      <refold_pos>false</refold_pos>
    </ion_control>
    <cell_control>
      <cell_dynamics>none</cell_dynamics>
      <pressure>0.000000000000000e0</pressure>
      <wmass>3.672227080435770e5</wmass>
      <cell_factor>0.000000000000000e0</cell_factor>
      <fix_volume>false</fix_volume>
      <fix_area>false</fix_area>
      <isotropic>false</isotropic>
    </cell_control>
    <symmetry_flags>
      <nosym>false</nosym>
      <nosym_evc>false</nosym_evc>
      <noinv>false</noinv>
      <no_t_rev>false</no_t_rev>
      <force_symmorphic>false</force_symmorphic>
      <use_all_frac>false</use_all_frac>
    </symmetry_flags>
  </input>
  <output>
    <convergence_info>
      <scf_conv>
        <convergence_achieved>false</convergence_achieved>
        <n_scf_steps>1</n_scf_steps>
        <scf_error>0.000000000000000e0</scf_error>
      </scf_conv>
    </convergence_info>
    <algorithmic_info>
      <real_space_q>false</real_space_q>
      <real_space_beta>false</real_space_beta>
      <uspp>true</uspp>
      <paw>true</paw>
    </algorithmic_info>
    <atomic_species ntyp="2" pseudo_dir="../../pseudo/">
      <species name="Si">
        <mass>2.808550000000000e1</mass>
        <pseudo_file>Si.pbe-rrkj.UPF</pseudo_file>
      </species>
      <species name="Ge">
        <mass>7.264000000000000e1</mass>
        <pseudo_file>Ge.pbe-kjpaw.UPF</pseudo_file>
      </species>
    </atomic_species>
    <atomic_structure nat="8" alat="1.034568287142e1">
      <atomic_positions>
        <atom name="Si" index="1">1.404406667437952e-3 1.404406667437952e-3 -4.473343261149537e-2</atom>
        <atom name="Si" index="2">2.587760345251342e0 2.587760345251342e0 2.517347977909821e0</atom>
        <atom name="Ge" index="3">5.174096277304679e0 1.115990995858547e-3 5.217030514893136e0</atom>
        <atom name="Ge" index="4">1.115990995858547e-3 5.174096277304679e0 5.217030514893136e0</atom>
        <atom name="Si" index="5">5.174106810638142e0 5.174106810638142e0 -4.501924801991594e-2</atom>
        <atom name="Ge" index="6">7.760456065260715e0 2.587475826195049e0 8.047598618895766e0</atom>
        <atom name="Ge" index="7">2.587475826195049e0 7.760456065260715e0 8.047598618895766e0</atom>
        <atom name="Si" index="8">7.760462539462447e0 7.760462539462447e0 2.517063043113779e0</atom>
      </atomic_positions>
      <cell>
        <a1>1.034568286400000e1 -2.734100000000000e-4 -2.808260000000000e-4</a1>
        <a2>-2.734100000000000e-4 1.034568286400000e1 -2.808260000000000e-4</a2>
        <a3>-2.734100000000000e-4 -2.734100000000000e-4 1.079211782200000e1</a3>
      </cell>
    </atomic_structure>
    <symmetries>
      <nsym>2</nsym>
      <nrot>4</nrot>
      <space_group>0</space_group>
      <symmetry>
        <info name="identity" class="not found">crystal_symmetry</info>
        <rotation rank="2" dims="3 3" order="F">
          1.000000000000000e0 0.000000000000000e0 0.000000000000000e0
          0.000000000000000e0 1.000000000000000e0 0.000000000000000e0
          0.000000000000000e0 0.000000000000000e0 1.000000000000000e0
          </rotation>
        <fractional_translation>0.000000000000000e0 0.000000000000000e0 0.000000000000000e0</fractional_translation>
        <equivalent_atoms nat="8" size="8">
          1 2 3 4 5 6 7 8
          </equivalent_atoms>
      </symmetry>
      <symmetry>
        <info name="inv. 180 deg rotation - cart. axis [1,-1,0]" class="not found">crystal_symmetry</info>
        <rotation rank="2" dims="3 3" order="F">
          0.000000000000000e0 1.000000000000000e0 0.000000000000000e0
          1.000000000000000e0 0.000000000000000e0 0.000000000000000e0
          0.000000000000000e0 0.000000000000000e0 1.000000000000000e0
          </rotation>
        <fractional_translation>0.000000000000000e0 0.000000000000000e0 0.000000000000000e0</fractional_translation>
        <equivalent_atoms nat="8" size="8">
          1 2 4 3 5 7 6 8
          </equivalent_atoms>
      </symmetry>
      <symmetry>
        <info name="inversion" class="not found">lattice_symmetry</info>
        <rotation rank="2" dims="3 3" order="F">
          -1.000000000000000e0 0.000000000000000e0 0.000000000000000e0
          0.000000000000000e0 -1.000000000000000e0 0.000000000000000e0
          0.000000000000000e0 0.000000000000000e0 -1.000000000000000e0
          </rotation>
      </symmetry>
      <symmetry>
        <info name="180 deg rotation - cart. axis [1,-1,0]" class="not found">lattice_symmetry</info>
        <rotation rank="2" dims="3 3" order="F">
          0.000000000000000e0 -1.000000000000000e0 0.000000000000000e0
          -1.000000000000000e0 0.000000000000000e0 0.000000000000000e0
          0.000000000000000e0 0.000000000000000e0 -1.000000000000000e0
          </rotation>
      </symmetry>
    </symmetries>
    <basis_set>
      <gamma_only>false</gamma_only>
      <ecutwfc>1.500000000000000e1</ecutwfc>
      <ecutrho>6.000000000000000e1</ecutrho>
      <fft_grid nr1="40" nr2="40" nr3="40"></fft_grid>
      <fft_smooth nr1="40" nr2="40" nr3="40"></fft_smooth>
      <fft_box nr1="40" nr2="40" nr3="40"></fft_box>
      <ngm>25689</ngm>
      <ngms>25689</ngms>
      <npwx>3210</npwx>
      <reciprocal_lattice>
        <b1>1.000000002103333e0 2.642813614798932e-5 2.533490004477236e-5</b1>
        <b2>2.642813614798932e-5 1.000000002103333e0 2.533490004477236e-5</b2>
        <b3>2.602208639030483e-5 2.602208639030483e-5 9.586332410640907e-1</b3>
      </reciprocal_lattice>
    </basis_set>
    <dft>
      <functional>PBE</functional>
    </dft>
    <magnetization>
      <lsda>false</lsda>
      <noncolin>false</noncolin>
      <spinorbit>false</spinorbit>
      <total>0.000000000000000e0</total>
      <absolute>0.000000000000000e0</absolute>
      <do_magnetization>false</do_magnetization>
    </magnetization>
    <total_energy>
      <etot>0.000000000000000e0</etot>
      <eband>0.000000000000000e0</eband>
      <ehart>2.251969856583011e0</ehart>
      <vtxc>-1.298952906283941e1</vtxc>
      <etxc>-3.712800683609099e1</etxc>
      <ewald>0.000000000000000e0</ewald>
      <demet>-4.563800771351229e-7</demet>
    </total_energy>
    <band_structure>
      <lsda>false</lsda>
      <noncolin>false</noncolin>
      <spinorbit>false</spinorbit>
      <nbnd>20</nbnd>
      <nelec>3.200000000000000e1</nelec>
      <num_of_atomic_wfc>32</num_of_atomic_wfc>
      <wf_collected>true</wf_collected>
      <fermi_energy>2.270846378623998e-1</fermi_energy>
      <starting_k_points>
        <nk>11</nk>
        <k_point weight="1.000000000000e0">0.000000000000000e0 0.000000000000000e0 0.000000000000000e0</k_point>
        <k_point weight="1.000000000000e0">1.301104319515242e-6 1.301104319515242e-6 4.793166205320453e-2</k_point>
        <k_point weight="1.000000000000e0">2.602208639030483e-6 2.602208639030483e-6 9.586332410640907e-2</k_point>
        <k_point weight="1.000000000000e0">3.903312958545725e-6 3.903312958545725e-6 1.437949861596136e-1</k_point>
        <k_point weight="1.000000000000e0">5.204417278060967e-6 5.204417278060967e-6 1.917266482128182e-1</k_point>
        <k_point weight="1.000000000000e0">6.505521597576208e-6 6.505521597576208e-6 2.396583102660227e-1</k_point>
        <k_point weight="1.000000000000e0">7.806625917091450e-6 7.806625917091450e-6 2.875899723192272e-1</k_point>
        <k_point weight="1.000000000000e0">9.107730236606692e-6 9.107730236606692e-6 3.355216343724318e-1</k_point>
        <k_point weight="1.000000000000e0">1.040883455612193e-5 1.040883455612193e-5 3.834532964256363e-1</k_point>
        <k_point weight="1.000000000000e0">1.170993887563717e-5 1.170993887563717e-5 4.313849584788408e-1</k_point>
        <k_point weight="1.000000000000e0">1.301104319515242e-5 1.301104319515242e-5 4.793166205320453e-1</k_point>
      </starting_k_points>
      <nks>11</nks>
      <occupations_kind>smearing</occupations_kind>
      <smearing degauss="5.000000000000e-4">gaussian</smearing>
      <ks_energies>
        <k_point weight="1.818181818182e-1">0.000000000000000e0 0.000000000000000e0 0.000000000000000e0</k_point>
        <npw>3191</npw>
        <eigenvalues size="20">
          -2.319080972063870e-1 -9.437828602437987e-2 -9.436889465634197e-2 -9.127162250651935e-2 -8.849752214327854e-2
          -6.874854793055469e-2 -6.873993815420531e-2 1.070571896662729e-1 1.070805442909951e-1 1.121170303071959e-1
          1.121410158977077e-1 1.188585119058203e-1 1.205559930369458e-1 2.111985507269512e-1 2.255366958983164e-1
          2.266280451817555e-1 2.323838775826039e-1 2.324129399916517e-1 2.512797131317772e-1 2.573078495752736e-1
          </eigenvalues>
        <occupations size="20">
          1.000000000000000e0 1.000000000000000e0 1.000000000000000e0 1.000000000000000e0 1.000000000000000e0
          1.000000000000000e0 1.000000000000000e0 1.000000000000000e0 1.000000000000000e0 1.000000000000000e0
          1.000000000000000e0 1.000000000000000e0 1.000000000000000e0 1.000000000000000e0 1.000000000000000e0
          9.951010053080854e-1 9.779643546434960e-198 6.946406609177071e-200 0.000000000000000e0 0.000000000000000e0
          </occupations>
      </ks_energies>
      <ks_energies>
        <k_point weight="1.818181818182e-1">1.301104319515242e-6 1.301104319515242e-6 4.793166205320453e-2</k_point>
        <npw>3171</npw>
        <eigenvalues size="20">
          -2.315463695622637e-1 -1.030499222321178e-1 -9.429214111377753e-2 -9.428257287992528e-2 -7.620950381365709e-2
          -6.865368868420076e-2 -6.864491520406657e-2 1.062595464523755e-1 1.062825371208069e-1 1.109734426522158e-1
          1.109969483640989e-1 1.191977013071949e-1 1.209139254866793e-1 2.069701451413852e-1 2.237277447597195e-1
          2.248316570850509e-1 2.345742975664123e-1 2.346038394527454e-1 2.505728831946326e-1 2.590806541582831e-1
          </eigenvalues>
        <occupations size="20">
          1.000000000000000e0 1.000000000000000e0 1.000000000000000e0 1.000000000000000e0 1.000000000000000e0
          1.000000000000000e0 1.000000000000000e0 1.000000000000000e0 1.000000000000000e0 1.000000000000000e0
          1.000000000000000e0 1.000000000000000e0 1.000000000000000e0 1.000000000000000e0 1.000000000000000e0
          1.000000000000000e0 0.000000000000000e0 0.000000000000000e0 0.000000000000000e0 0.000000000000000e0
          </occupations>
      </ks_energies>
      <ks_energies>
        <k_point weight="1.818181818182e-1">2.602208639030483e-6 2.602208639030483e-6 9.586332410640907e-2</k_point>
        <npw>3187</npw>
        <eigenvalues size="20">
          -2.304634367101751e-1 -1.155668169173707e-1 -9.404258835329626e-2 -9.403251932686672e-2 -6.837941860428729e-2
          -6.837018252160241e-2 -6.216903701762987e-2 1.040074714253695e-1 1.040294253020853e-1 1.078157364791493e-1
          1.078379226798121e-1 1.202111249078253e-1 1.219817971248194e-1 1.963108570011089e-1 2.188032273995119e-1
          2.199429704124943e-1 2.408665284390867e-1 2.408973624969112e-1 2.495744505396194e-1 2.642393996105772e-1
          </eigenvalues>
        <occupations size="20">
          1.000000000000000e0 1.000000000000000e0 1.000000000000000e0 1.000000000000000e0 1.000000000000000e0
          1.000000000000000e0 1.000000000000000e0 1.000000000000000e0 1.000000000000000e0 1.000000000000000e0
          1.000000000000000e0 1.000000000000000e0 1.000000000000000e0 1.000000000000000e0 1.000000000000000e0
          1.000000000000000e0 0.000000000000000e0 0.000000000000000e0 0.000000000000000e0 0.000000000000000e0
          </occupations>
      </ks_energies>
      <ks_energies>
        <k_point weight="1.818181818182e-1">3.903312958545725e-6 3.903312958545725e-6 1.437949861596136e-1</k_point>
        <npw>3183</npw>
        <eigenvalues size="20">
          -2.286628887911030e-1 -1.275346099066048e-1 -9.364864386056439e-2 -9.363782578405324e-2 -6.794582799807719e-2
          -6.793589900152691e-2 -4.767039933500766e-2 1.006714207467200e-1 1.006917994134431e-1 1.032968929402156e-1
          1.033171795315675e-1 1.218895539957412e-1 1.237586810967027e-1 1.823149065558355e-1 2.118288624989489e-1
          2.130515938680579e-1 2.491078743001141e-1 2.506355822251014e-1 2.506682131049003e-1 2.698175877765149e-1
          </eigenvalues>
        <occupations size="20">
          1.000000000000000e0 1.000000000000000e0 1.000000000000000e0 1.000000000000000e0 1.000000000000000e0
          1.000000000000000e0 1.000000000000000e0 1.000000000000000e0 1.000000000000000e0 1.000000000000000e0
          1.000000000000000e0 1.000000000000000e0 1.000000000000000e0 1.000000000000000e0 1.000000000000000e0
          1.000000000000000e0 0.000000000000000e0 0.000000000000000e0 0.000000000000000e0 0.000000000000000e0
          </occupations>
      </ks_energies>
      <ks_energies>
        <k_point weight="1.818181818182e-1">5.204417278060967e-6 5.204417278060967e-6 1.917266482128182e-1</k_point>
        <npw>3207</npw>
        <eigenvalues size="20">
          -2.261527496084643e-1 -1.389056213183417e-1 -9.314608776267953e-2 -9.313436867085445e-2 -6.739162012109073e-2
          -6.738085706718694e-2 -3.277751534582288e-2 9.671658928359925e-2 9.673500753994016e-2 9.813829096198457e-2
          9.815633809550825e-2 1.242113587075041e-1 1.262384540303622e-1 1.667641432379452e-1 2.037584626703977e-1
          2.051264515951960e-1 2.493116415868800e-1 2.631642453210016e-1 2.631989143921860e-1 2.751962972222455e-1
          </eigenvalues>
        <occupations size="20">
          1.000000000000000e0 1.000000000000000e0 1.000000000000000e0 1.000000000000000e0 1.000000000000000e0
          1.000000000000000e0 1.000000000000000e0 1.000000000000000e0 1.000000000000000e0 1.000000000000000e0
          1.000000000000000e0 1.000000000000000e0 1.000000000000000e0 1.000000000000000e0 1.000000000000000e0
          1.000000000000000e0 0.000000000000000e0 0.000000000000000e0 0.000000000000000e0 0.000000000000000e0
          </occupations>
      </ks_energies>
      <ks_energies>
        <k_point weight="1.818181818182e-1">6.505521597576208e-6 6.505521597576208e-6 2.396583102660227e-1</k_point>
        <npw>3191</npw>
        <eigenvalues size="20">
          -2.229463340284238e-1 -1.496418406523093e-1 -9.257852624788612e-2 -9.256585084737758e-2 -6.676371880528889e-2
          -6.675207022383375e-2 -1.754645635925853e-2 9.260267087100347e-2 9.261888002184502e-2 9.295060227744395e-2
          9.296623850619914e-2 1.271460725655555e-1 1.294120497122050e-1 1.505084880139808e-1 1.952399810939945e-1
          1.968487735040394e-1 2.501850069052853e-1 2.778846986056168e-1 2.779214868296196e-1 2.806989956223863e-1
          </eigenvalues>
        <occupations size="20">
          1.000000000000000e0 1.000000000000000e0 1.000000000000000e0 1.000000000000000e0 1.000000000000000e0
          1.000000000000000e0 1.000000000000000e0 1.000000000000000e0 1.000000000000000e0 1.000000000000000e0
          1.000000000000000e0 1.000000000000000e0 1.000000000000000e0 1.000000000000000e0 1.000000000000000e0
          1.000000000000000e0 0.000000000000000e0 0.000000000000000e0 0.000000000000000e0 0.000000000000000e0
          </occupations>
      </ks_energies>
      <ks_energies>
        <k_point weight="1.818181818182e-1">7.806625917091450e-6 7.806625917091450e-6 2.875899723192272e-1</k_point>
        <npw>3195</npw>
        <eigenvalues size="20">
          -2.190696929609750e-1 -1.597015014762939e-1 -9.200147288104581e-2 -9.198787447707346e-2 -6.612329138346526e-2
          -6.611078757730010e-2 -2.052023865288311e-3 8.819016798124535e-2 8.820333788035251e-2 8.872040297033507e-2
          8.873427450117257e-2 1.306306690427517e-1 1.332682386463006e-1 1.339645806073340e-1 1.866785847679295e-1
          1.886627301514089e-1 2.516715436980879e-1 2.847655379713160e-1 2.943451274334167e-1 2.943840152242505e-1
          </eigenvalues>
        <occupations size="20">
          1.000000000000000e0 1.000000000000000e0 1.000000000000000e0 1.000000000000000e0 1.000000000000000e0
          1.000000000000000e0 1.000000000000000e0 1.000000000000000e0 1.000000000000000e0 1.000000000000000e0
          1.000000000000000e0 1.000000000000000e0 1.000000000000000e0 1.000000000000000e0 1.000000000000000e0
          1.000000000000000e0 0.000000000000000e0 0.000000000000000e0 0.000000000000000e0 0.000000000000000e0
          </occupations>
      </ks_energies>
      <ks_energies>
        <k_point weight="1.818181818182e-1">9.107730236606692e-6 9.107730236606692e-6 3.355216343724318e-1</k_point>
        <npw>3185</npw>
        <eigenvalues size="20">
          -2.145775583957843e-1 -1.690159441236538e-1 -9.147176362524888e-2 -9.145735387856019e-2 -6.553368072406811e-2
          -6.552042398847936e-2 1.358689659643953e-2 8.418750042063476e-2 8.419825743837063e-2 8.538469778021383e-2
          8.539623116162932e-2 1.174201558749696e-1 1.345431034598574e-1 1.377831101168359e-1 1.783366616254070e-1
          1.809285676431074e-1 2.536427845322046e-1 2.851210756744533e-1 3.097208182335413e-1 3.122293894786926e-1
          </eigenvalues>
        <occupations size="20">
          1.000000000000000e0 1.000000000000000e0 1.000000000000000e0 1.000000000000000e0 1.000000000000000e0
          1.000000000000000e0 1.000000000000000e0 1.000000000000000e0 1.000000000000000e0 1.000000000000000e0
          1.000000000000000e0 1.000000000000000e0 1.000000000000000e0 1.000000000000000e0 1.000000000000000e0
          1.000000000000000e0 0.000000000000000e0 0.000000000000000e0 0.000000000000000e0 0.000000000000000e0
          </occupations>
      </ks_energies>
      <ks_energies>
        <k_point weight="1.818181818182e-1">1.040883455612193e-5 1.040883455612193e-5 3.834532964256363e-1</k_point>
        <npw>3199</npw>
        <eigenvalues size="20">
          -2.096113741403771e-1 -1.774338007713554e-1 -9.104559757227076e-2 -9.103055560274052e-2 -6.505819845941925e-2
          -6.504435434029911e-2 2.910887189146690e-2 8.117449839799512e-2 8.118305744327936e-2 8.283289516895264e-2
          8.284227799342098e-2 1.012169494549989e-1 1.386108214630957e-1 1.429224295186018e-1 1.703832038581047e-1
          1.740499139945319e-1 2.558464571219833e-1 2.826621134842740e-1 3.167529696990210e-1 3.312575036844862e-1
          </eigenvalues>
        <occupations size="20">
          1.000000000000000e0 1.000000000000000e0 1.000000000000000e0 1.000000000000000e0 1.000000000000000e0
          1.000000000000000e0 1.000000000000000e0 1.000000000000000e0 1.000000000000000e0 1.000000000000000e0
          1.000000000000000e0 1.000000000000000e0 1.000000000000000e0 1.000000000000000e0 1.000000000000000e0
          1.000000000000000e0 0.000000000000000e0 0.000000000000000e0 0.000000000000000e0 0.000000000000000e0
          </occupations>
      </ks_energies>
      <ks_energies>
        <k_point weight="1.818181818182e-1">1.170993887563717e-5 1.170993887563717e-5 4.313849584788408e-1</k_point>
        <npw>3202</npw>
        <eigenvalues size="20">
          -2.046696929913427e-1 -1.844491267136382e-1 -9.076915472366947e-2 -9.075371002812428e-2 -6.474896995211788e-2
          -6.473475186525012e-2 4.359340860288929e-2 7.930665983135342e-2 7.931353748466558e-2 8.123566255254744e-2
          8.124340910259081e-2 8.631370514862198e-2 1.421619283933808e-1 1.485505860887775e-1 1.630386932912088e-1
          1.687867086665964e-1 2.577738736667350e-1 2.799941396944813e-1 3.255706528240428e-1 3.453403429953790e-1
          </eigenvalues>
        <occupations size="20">
          1.000000000000000e0 1.000000000000000e0 1.000000000000000e0 1.000000000000000e0 1.000000000000000e0
          1.000000000000000e0 1.000000000000000e0 1.000000000000000e0 1.000000000000000e0 1.000000000000000e0
          1.000000000000000e0 1.000000000000000e0 1.000000000000000e0 1.000000000000000e0 1.000000000000000e0
          1.000000000000000e0 0.000000000000000e0 0.000000000000000e0 0.000000000000000e0 0.000000000000000e0
          </occupations>
      </ks_energies>
      <ks_energies>
        <k_point weight="1.818181818182e-1">1.301104319515242e-5 1.301104319515242e-5 4.793166205320453e-1</k_point>
        <npw>3210</npw>
        <eigenvalues size="20">
          -2.019703413879465e-1 -1.878402040582997e-1 -9.067364994770017e-2 -9.065806698961067e-2 -6.464217657608002e-2
          -6.462782989455079e-2 5.169122701952142e-2 7.807465387032985e-2 7.867420612641114e-2 7.868041678487017e-2
          8.069204302107924e-2 8.069914860837292e-2 1.437307677472610e-1 1.529117447651394e-1 1.581006266030402e-1
          1.666420982596487e-1 2.585906744676688e-1 2.788590507259447e-1 3.325145543293302e-1 3.389982539886054e-1
          </eigenvalues>
        <occupations size="20">
          1.000000000000000e0 1.000000000000000e0 1.000000000000000e0 1.000000000000000e0 1.000000000000000e0
          1.000000000000000e0 1.000000000000000e0 1.000000000000000e0 1.000000000000000e0 1.000000000000000e0
          1.000000000000000e0 1.000000000000000e0 1.000000000000000e0 1.000000000000000e0 1.000000000000000e0
          1.000000000000000e0 0.000000000000000e0 0.000000000000000e0 0.000000000000000e0 0.000000000000000e0
          </occupations>
      </ks_energies>
    </band_structure>
  </output>
  <status>0</status>
  <timing_info>
    <total label="PWSCF">
      <cpu>1.785568700000000e1</cpu>
      <wall>1.788387989997864e1</wall>
    </total>
    <partial label="electrons" calls="1">
      <cpu>1.651095500000000e1</cpu>
      <wall>1.652714109420776e1</wall>
    </partial>
  </timing_info>
  <closed DATE="26 Oct 2021" TIME="18:16:23"></closed>
</qes:espresso>
